pubmed_mapper.py
pubmed_mapper-0.1.1.dist-info/METADATA
pubmed_mapper-0.1.1.dist-info/WHEEL
pubmed_mapper-0.1.1.dist-info/entry_points.txt
pubmed_mapper-0.1.1.dist-info/top_level.txt
pubmed_mapper-0.1.1.dist-info/RECORD
