Metadata-Version: 2.1
Name: pubmed-mapper
Version: 0.1.1
Summary: PubMed Mapper: A Python library that map PubMed XML to Python object
Home-page: https://github.com/soultoolman/pubmed-mapper
Author: soultoolman
Author-email: soultooman@gmail.com
License: MIT
Platform: UNKNOWN
Classifier: License :: OSI Approved :: MIT License
Classifier: Programming Language :: Python
Classifier: Programming Language :: Python :: 3
Classifier: Programming Language :: Python :: 3.6
Classifier: Programming Language :: Python :: Implementation :: CPython
Classifier: Programming Language :: Python :: Implementation :: PyPy
Classifier: Topic :: Scientific/Engineering :: Bio-Informatics
Requires-Python: >=3.6.0
Requires-Dist: lxml
Requires-Dist: click
Requires-Dist: rich
